billy_penn/__init__.py
billy_penn/data/dept_names_lookup.xlsx
billy_penn/data/depts.json
billy_penn/departments.py
billy_penn-0.1.11.dist-info/LICENSE
billy_penn-0.1.11.dist-info/METADATA
billy_penn-0.1.11.dist-info/WHEEL
billy_penn-0.1.11.dist-info/RECORD
